<?xml version="1.0" encoding="UTF-8"?>
<odoo>

    <record id="sale_order_inherit_quickcreate_form" model="ir.ui.view">
        <field name="name">sale.order.quickcreate.form</field>
        <field name="model">sale.order</field>
        <field name="type">form</field>
        <field name="inherit_id" ref="sale.view_order_form"/>
        <field name="arch" type="xml">

            <xpath expr="//group[@name='partner_details']/field[@name='partner_id']" position="attributes">
                <attribute name="options">{'no_quick_create':True,'no_create_edit':True,'no_open': True,'no_create': True}</attribute>
            </xpath>

            <xpath expr="//field[@name='order_line']/tree/field[@name='product_id']" position="attributes">
                <attribute name="options">{'no_quick_create':True,'no_create_edit':True,'no_open': True,'no_create': True}</attribute>
            </xpath>

            <xpath expr="//field[@name='order_line']/tree/field[@name='product_uom']" position="attributes">
                <attribute name="options">{'no_quick_create':True,'no_create_edit':True,'no_open': True,'no_create': True}</attribute>
            </xpath>

            <xpath expr="//page[@name='other_information']/group/group[@name='sales_person']/field[@name='user_id']" position="attributes">
                <attribute name="options">{'no_quick_create':True,'no_create_edit':True,'no_open': True,'no_create': True}</attribute>
            </xpath>

            <xpath expr="//page[@name='other_information']/group/group[@name='sales_person']/field[@name='company_id']" position="attributes">
                <attribute name="options">{'no_quick_create':True,'no_create_edit':True,'no_open': True,'no_create': True}</attribute>
            </xpath>

        </field>
    </record>

    <record id="sale_order_inherit_quickcreatet1_form" model="ir.ui.view">
        <field name="name">sale.order.quickcreatet1.form</field>
        <field name="model">sale.order</field>
        <field name="type">form</field>
        <field name="inherit_id" ref="sale_management.sale_order_form_quote"/>
        <field name="arch" type="xml">

            <xpath expr="//field[@name='sale_order_option_ids']/tree/field[@name='product_id']" position="attributes">
                <attribute name="options">{'no_quick_create':True,'no_create_edit':True,'no_open': True,'no_create': True}</attribute>
            </xpath>

            <xpath expr="//field[@name='sale_order_option_ids']/tree/field[@name='uom_id']" position="attributes">
                <attribute name="options">{'no_quick_create':True,'no_create_edit':True,'no_open': True,'no_create': True}</attribute>
            </xpath>

        </field>
    </record>

    <record id="sale_order_inherit_quickcreatet2_form" model="ir.ui.view">
        <field name="name">sale.order.quickcreatet2.form</field>
        <field name="model">sale.order</field>
        <field name="type">form</field>
        <field name="inherit_id" ref="sale_stock.view_order_form_inherit_sale_stock"/>
        <field name="arch" type="xml">

            <xpath expr="//group[@name='sale_shipping']/field[@name='warehouse_id']" position="attributes">
                <attribute name="options">{'no_quick_create':True,'no_create_edit':True,'no_open': True,'no_create': True}</attribute>
            </xpath>

        </field>
    </record>

</odoo>